hagrid/__init__.py
hagrid/art.py
hagrid/auth.py
hagrid/azure.py
hagrid/cache.py
hagrid/cli.py
hagrid/deps.py
hagrid/dummynum.py
hagrid/exceptions.py
hagrid/file.py
hagrid/git_check.py
hagrid/grammar.py
hagrid/land.py
hagrid/launch.py
hagrid/lib.py
hagrid/manifest_template.yml
hagrid/mode.py
hagrid/names.py
hagrid/nb_output.py
hagrid/orchestra.py
hagrid/parse_template.py
hagrid/quickstart_ui.py
hagrid/rand_sec.py
hagrid/stable_version.py
hagrid/style.py
hagrid/util.py
hagrid/version.py
hagrid/win_bootstrap.py
hagrid/wizard_ui.py
tests/__init__.py
tests/hagrid/__init__.py
tests/hagrid/cli_test.py
hagrid-0.3.124.dist-info/METADATA
hagrid-0.3.124.dist-info/WHEEL
hagrid-0.3.124.dist-info/entry_points.txt
hagrid-0.3.124.dist-info/top_level.txt
hagrid-0.3.124.dist-info/RECORD
